
	
{
	"title": "Seizoenstype",
	"description": "Stylisten bepalen op basis van iemands haar-, huid- en oogkleur of iemand een zomer-, herfst-, winter- of lentetype is, of een type tussen twee seizoenstypes in is.",
	"tools": null,
	"semester": null,
	"weight": null,
	"tags": null,
	"pillar": null,
	"tracks": null,
	"content": "\u003cp\u003eStylisten bepalen op basis van iemands haar-, huid- en oogkleur of iemand een zomer-, herfst-, winter- of lentetype is, of een type tussen twee seizoenstypes in is. Acht in totaal dus: winter, winter-lente, lente, \u0026hellip; Met een Convolutional Neural Net word jij als één van de types geclassificeerd en wordt dan de juist kledingstijl daaraan gekoppeld.\u003c/p\u003e\n"
}

